dataverse_rest_api/__init__.py
dataverse_rest_api/client.py
dataverse_rest_api-0.4.5.dist-info/METADATA
dataverse_rest_api-0.4.5.dist-info/WHEEL
dataverse_rest_api-0.4.5.dist-info/top_level.txt
dataverse_rest_api-0.4.5.dist-info/RECORD
